timezones/__init__.py
timezones/admin.py
timezones/app_settings.py
timezones/apps.py
timezones/auth_hooks.py
timezones/constants.py
timezones/models.py
timezones/urls.py
timezones/views.py
timezones/aadiscordbot/cogs/time.py
timezones/locale/django.pot
timezones/locale/cs_CZ/LC_MESSAGES/django.mo
timezones/locale/cs_CZ/LC_MESSAGES/django.po
timezones/locale/de/LC_MESSAGES/django.mo
timezones/locale/de/LC_MESSAGES/django.po
timezones/locale/es/LC_MESSAGES/django.mo
timezones/locale/es/LC_MESSAGES/django.po
timezones/locale/fr_FR/LC_MESSAGES/django.mo
timezones/locale/fr_FR/LC_MESSAGES/django.po
timezones/locale/it_IT/LC_MESSAGES/django.mo
timezones/locale/it_IT/LC_MESSAGES/django.po
timezones/locale/ja/LC_MESSAGES/django.mo
timezones/locale/ja/LC_MESSAGES/django.po
timezones/locale/ko_KR/LC_MESSAGES/django.mo
timezones/locale/ko_KR/LC_MESSAGES/django.po
timezones/locale/nl_NL/LC_MESSAGES/django.mo
timezones/locale/nl_NL/LC_MESSAGES/django.po
timezones/locale/pl_PL/LC_MESSAGES/django.mo
timezones/locale/pl_PL/LC_MESSAGES/django.po
timezones/locale/ru/LC_MESSAGES/django.mo
timezones/locale/ru/LC_MESSAGES/django.po
timezones/locale/sk/LC_MESSAGES/django.mo
timezones/locale/sk/LC_MESSAGES/django.po
timezones/locale/uk/LC_MESSAGES/django.mo
timezones/locale/uk/LC_MESSAGES/django.po
timezones/locale/zh_Hans/LC_MESSAGES/django.mo
timezones/locale/zh_Hans/LC_MESSAGES/django.po
timezones/management/commands/timezones_load_tz_data.py
timezones/migrations/0001_initial.py
timezones/migrations/0002_timezonedata_timezones.py
timezones/migrations/0003_auto_20201003_1748.py
timezones/migrations/0004_delete_aatimezones.py
timezones/migrations/0005_alter_timezonedata_options.py
timezones/migrations/__init__.py
timezones/static/timezones/css/timezones.css
timezones/static/timezones/css/timezones.min.css
timezones/static/timezones/css/timezones.min.css.map
timezones/static/timezones/js/timezones.js
timezones/static/timezones/js/timezones.min.js
aa_timezones-2.4.4.dist-info/METADATA
aa_timezones-2.4.4.dist-info/WHEEL
aa_timezones-2.4.4.dist-info/licenses/LICENSE
aa_timezones-2.4.4.dist-info/RECORD
